{
  "schema_version": "moomooau.stage5-verification.v1",
  "stage_id": "S5",
  "status": "PASS",
  "observed_at_utc": "2026-07-20T03:21:33Z",
  "baseline_commit": "9394585329a52c4d269da220bd66ce8ec9b820b3",
  "scope": "LOCAL_SYNTHETIC_ONLY",
  "task_pass_count": 7,
  "task_total": 7,
  "stage5_task_tests_passed": 21,
  "cumulative_task_tests_passed": 116,
  "final_acceptance_policy": "NOT_FINAL",
  "final_acceptances_passed": 0,
  "protected_oracles_executed": 0,
  "stage5_observation": {
    "synthetic_recovery_proofs_issued": 2,
    "synthetic_corrupt_recovery_authorizations": 0,
    "synthetic_gmail_mutations": 2,
    "real_gmail_calls": 0,
    "real_gmail_mutations": 0,
    "private_repository_calls": 0,
    "thread_trash_calls": 0,
    "permanent_delete_calls": 0,
    "persistent_plaintext_objects": 0,
    "release_assets_above_one": 0,
    "stranded_uncertain_or_corrupt_assets": 0,
    "production_workflow_runs": 0,
    "dependency_advisory_scan": "PASS",
    "known_vulnerabilities_observed": 0,
    "local_secret_scan_findings": 0,
    "package_build_smoke": "PASS",
    "taskpack_validation": "PASS",
    "governance_validation": "PASS",
    "digest_pinned_container_build": "PASS",
    "network_none_read_only_container_smoke": "PASS",
    "private_remote_recovery": "NOT_RUN",
    "real_source_message_trash": "NOT_RUN",
    "real_live_release_replacement": "NOT_RUN",
    "remote_stage5_ci": "NOT_RUN",
    "protected_schedule_execution": "NOT_RUN"
  },
  "prohibition_counters": {"real_gmail_calls": 0, "gmail_mutations": 0, "private_repository_calls": 0, "real_secrets_read": 0, "protected_key_deliveries": 0, "external_writes": 0, "remote_publication": 0, "non_moomoo_full_reads": 0, "non_moomoo_downloads": 0, "non_moomoo_mutations": 0, "raw_before_verification": 0, "untrusted_content_execution": 0, "moomoo_portal_calls": 0, "persistent_plaintext_objects": 0, "thread_trash_calls": 0, "permanent_delete_calls": 0, "release_assets_above_one": 0, "production_workflow_runs": 0},
  "delivery_status": "LOCAL_ONLY_NOT_PUBLISHED",
  "next_stage": "S6",
  "next_stage_status": "NOT_STARTED"
}
