{
  "schema": "PFIV025FormulaRegistryV1",
  "registry_version": "pfi-v0.2.5-formula-registry-v1",
  "base_currency": "CNY",
  "fx_contract": {
    "pair": "AUD/CNY",
    "direction": "AUD_TO_CNY",
    "definition_zh": "1 AUD = X CNY",
    "rate_unit": "CNY/AUD",
    "example_rate": "4.81",
    "example_only": true,
    "production_default": null
  },
  "lifecycle": {
    "statuses": ["draft", "active", "deprecated", "superseded"],
    "active_versions_immutable": true,
    "replacement_rule_zh": "活动版本不得原地改写；变更必须发布新 version，并把旧版本标记 deprecated 或 superseded，历史报告继续绑定原 hash。"
  },
  "formulas": [
    {
      "formula_id": "FORM-PFI-001",
      "version": "pfi-v0.2-product-scope-v1",
      "label_zh": "PFI 产品能力边界",
      "definition_zh": "按 Stage 能力并集减去真实付款、下单和自动交易禁区，确定本地财务中枢可发布范围。",
      "inputs": ["stage_capability_contracts", "forbidden_execution_actions"],
      "output": "publishable_product_scope",
      "outputs": ["publishable_product_scope"],
      "unit": "policy set",
      "parameters": ["PARAM-PFI-001..023"],
      "boundaries_zh": ["不提交付款、券商订单或自动交易。", "缺生产证据时不得标记 production ready。"],
      "dependencies": ["MOD-PFI-001"],
      "test_refs": ["PFI/tests/test_stage6_e2e_stabilization.py"],
      "effective_from": "2026-07-15",
      "formula_hash": "sha256:763b7898a39259545405d1a21516b2d91273c39e6786e873be9c209d74a0902e",
      "validation_status": "validated",
      "lifecycle_status": "active",
      "historical_compatibility_zh": "保留既有 FORM-PFI-001 ID 与产品边界，不改变历史 Stage 结果。"
    },
    {
      "formula_id": "FORM-PFI-002",
      "version": "pfi-v0.2.5-fx-business-date-v1",
      "label_zh": "FX 有效业务日",
      "definition_zh": "以 Australia/Sydney 本地日、06:00 cutoff、周末和显式闭市日向前滚动得到有效业务日。",
      "inputs": ["local_date", "local_time", "explicit_source_closed_dates"],
      "output": "effective_business_date",
      "outputs": ["effective_business_date", "snapshot_status"],
      "unit": "ISO local business date",
      "parameters": ["PARAM-PFI-024", "PARAM-PFI-025", "PARAM-PFI-026", "PARAM-PFI-027"],
      "boundaries_zh": ["普通运行不联网刷新。", "缺 source、方向或快照时 rate 保持 null。"],
      "dependencies": ["MOD-PFI-002", "SRC-FX-SNAPSHOT"],
      "test_refs": ["PFI/tests/test_v025_stage2_fx_policy.py", "PFI/tests/test_v025_stage2_temporal_truth.py"],
      "effective_from": "2026-07-15",
      "formula_hash": "sha256:8c9a9d51ad402c3b729464a9b791b973e0af9a07b17fc15d581b47cff6895c82",
      "validation_status": "validated",
      "lifecycle_status": "active",
      "historical_compatibility_zh": "沿用 Stage 2 已验收时间与 FX 状态合同，不提升旧示例汇率。"
    },
    {
      "formula_id": "FORM-PFI-003",
      "version": "pfi-v0.2.5-account-role-v1",
      "label_zh": "账户角色发布决策",
      "definition_zh": "只有显式角色注册表中的 proposed_role 才可发布，未知角色进入人工复核。",
      "inputs": ["proposed_role", "role_registry", "effective_range"],
      "output": "role_decision",
      "outputs": ["role_decision", "publish_allowed", "review_required"],
      "unit": "policy decision",
      "parameters": ["PARAM-PFI-028..035"],
      "boundaries_zh": ["不得从来源名、文件名或 provider 猜测角色。", "未知角色不得发布。"],
      "dependencies": ["MOD-PFI-003"],
      "test_refs": ["PFI/tests/test_v025_stage3_source_profiles.py"],
      "effective_from": "2026-07-15",
      "formula_hash": "sha256:f972e6a469fd4abe12e22aff0a0d2c291bf0eeba1fd5dadda57aa19d3931b46b",
      "validation_status": "validated",
      "lifecycle_status": "active",
      "historical_compatibility_zh": "保留 Stage 3.1 fail-closed 角色路由。"
    },
    {
      "formula_id": "FORM-PFI-004",
      "version": "pfi-v0.2.5-economic-event-identity-v1",
      "label_zh": "经济事件确定性身份",
      "definition_zh": "由来源记录身份、显式分组成员与版本化事件策略逐层计算 normalized、group 和 economic_event ID。",
      "inputs": ["source_record_identity", "group_members", "event_policy"],
      "output": "economic_event_id",
      "outputs": ["normalized_id", "group_id", "economic_event_id"],
      "unit": "deterministic identity",
      "parameters": ["PARAM-PFI-036..047"],
      "boundaries_zh": ["不得按金额相等或时间接近启发式分组。", "未知事件类型不得发布。"],
      "dependencies": ["MOD-PFI-004"],
      "test_refs": ["PFI/tests/test_v025_stage3_interconnection.py"],
      "effective_from": "2026-07-15",
      "formula_hash": "sha256:589cba10e6ea0b1b6651514f0f93957b444c712aa344fe66943e75e307cf926f",
      "validation_status": "validated",
      "lifecycle_status": "active",
      "historical_compatibility_zh": "保留 Stage 3.2 已验收 deterministic IDs。"
    },
    {
      "formula_id": "FORM-PFI-005",
      "version": "pfi-v0.2.5-ledger-idempotency-v1",
      "label_zh": "账本幂等键",
      "definition_zh": "对完整事件 lineage、影响标记和排序后 postings 做 canonical JSON SHA256，得到账本幂等键。",
      "inputs": ["ledger_lineage", "postings"],
      "output": "ledger_idempotency_key",
      "outputs": ["ledger_idempotency_key", "ledger_event_id"],
      "unit": "sha256 identity",
      "parameters": ["PARAM-PFI-036..047"],
      "boundaries_zh": ["不同币种金额不得在无 FX 政策时聚合。", "不完整 lineage 禁止发布。"],
      "dependencies": ["FORM-PFI-004", "MOD-PFI-004"],
      "test_refs": ["PFI/tests/test_v025_stage3_interconnection.py"],
      "effective_from": "2026-07-15",
      "formula_hash": "sha256:489c52156bfd7078bf587377fc0c83e4fa014052d5c354a584d941dd6497a30b",
      "validation_status": "validated",
      "lifecycle_status": "active",
      "historical_compatibility_zh": "保留 Stage 3.2 canonical serialization 和幂等身份。"
    },
    {
      "formula_id": "FORM-PFI-006",
      "version": "pfi-v0.2.5-ledger-publication-v1",
      "label_zh": "真实记录发布与复核路由",
      "definition_zh": "仅接受上游状态、非零金额、结构化映射完整且无必需关联缺口的记录，并按幂等键只发布一次。",
      "inputs": ["real_source_record", "publication_registry"],
      "output": "publication_decision",
      "outputs": ["published_ledger_event", "review_item"],
      "unit": "record decision",
      "parameters": ["PARAM-PFI-048..057"],
      "boundaries_zh": ["未决 transfer/refund 不发布。", "不使用金融 fixture fallback。"],
      "dependencies": ["FORM-PFI-004", "FORM-PFI-005", "MOD-PFI-005"],
      "test_refs": ["PFI/tests/test_v025_stage3_idempotency.py"],
      "effective_from": "2026-07-15",
      "formula_hash": "sha256:c761d3074c61074457669d3902ec3ca53f493a38044f1cb94c6951010c8f4bb7",
      "validation_status": "validated",
      "lifecycle_status": "active",
      "historical_compatibility_zh": "保留 Stage 3.3 review queue 与 insert-once 边界。"
    },
    {
      "formula_id": "FORM-PFI-007",
      "version": "pfi-v0.2.5-event-dedup-read-model-v1",
      "label_zh": "经济事件去重与页面快照",
      "definition_zh": "每个 metric 对 economic_event_id 去重，并由事件集合与幂等键集合生成页面无关 read-model hash。",
      "inputs": ["economic_event_set", "page_binding"],
      "output": "read_model_hash",
      "outputs": ["metric_event_set", "read_model_hash"],
      "unit": "event set and sha256 identity",
      "parameters": ["PARAM-PFI-048..057"],
      "boundaries_zh": ["同一经济事件对同一指标最多计数一次。", "证据不得包含私有金额或身份。"],
      "dependencies": ["FORM-PFI-006", "MOD-PFI-005"],
      "test_refs": ["PFI/tests/test_v025_stage3_no_double_count.py"],
      "effective_from": "2026-07-15",
      "formula_hash": "sha256:da77147d135d666f8b024a98c77895dec3bd4482b6902269be9c3d1252b568c7",
      "validation_status": "validated",
      "lifecycle_status": "active",
      "historical_compatibility_zh": "保留 Stage 3.3 去重与跨页身份合同。"
    },
    {
      "formula_id": "FORM-PFI-008",
      "version": "pfi-v0.2.5-account-reconciliation-v1",
      "label_zh": "账户余额精确对账",
      "definition_zh": "expected closing 等于 opening、confirmed net flows 与 adjustments 之和；差异为 observed closing 减 expected closing。",
      "inputs": ["opening_balance", "confirmed_net_flows", "adjustments", "observed_closing_balance"],
      "output": "account_balance_metric_state",
      "outputs": ["expected_closing_balance", "discrepancy", "account_balance_metric_state"],
      "unit": "source currency",
      "parameters": ["PARAM-PFI-058", "PARAM-PFI-059", "PARAM-PFI-060"],
      "boundaries_zh": ["精确 Decimal 零差异，不引入未解释容差。", "缺快照、coverage 或 lineage 时 value 为 null。"],
      "dependencies": ["MOD-PFI-006", "SRC-ACCOUNT-BALANCES"],
      "test_refs": ["PFI/tests/test_v025_stage4_accounts_read_model.py", "PFI/tests/test_v025_stage4_metric_states.py"],
      "effective_from": "2026-07-15",
      "formula_hash": "sha256:180bb3a18fc0c920518238c214103c841cd47632df558d50abdb3bd39be09f6a",
      "validation_status": "validated",
      "lifecycle_status": "active",
      "historical_compatibility_zh": "保留 Stage 4.1 无假零和不由交易推断余额的合同。"
    },
    {
      "formula_id": "FORM-PFI-009",
      "version": "pfi-v0.2.5-cost-basis-v1",
      "label_zh": "显式持仓成本基础",
      "definition_zh": "原币成本基础等于不含费用的 acquisition cost 加显式资本化费用，且成本方法必须登记。",
      "inputs": ["acquisition_cost_ex_fees", "capitalized_fee_total", "cost_basis_method"],
      "output": "cost_basis_original",
      "outputs": ["cost_basis_original"],
      "unit": "original currency",
      "parameters": ["PARAM-PFI-061..067"],
      "boundaries_zh": ["费用不得推断为已含或未含。", "未知成本方法不得计算。"],
      "dependencies": ["MOD-PFI-007", "SRC-HOLDINGS"],
      "test_refs": ["PFI/tests/test_v025_stage4_holdings_valuation.py"],
      "effective_from": "2026-07-15",
      "formula_hash": "sha256:ad9e524713a07eec129735a3c13e94692eaa6a05d6939a0e3ea107999d2ef972",
      "validation_status": "validated",
      "lifecycle_status": "active",
      "historical_compatibility_zh": "保留 Stage 4.2 显式成本方法与费用合同。"
    },
    {
      "formula_id": "FORM-PFI-010",
      "version": "pfi-v0.2.5-holding-valuation-v1",
      "label_zh": "持仓时点估值",
      "definition_zh": "原币市值等于 quantity 乘 price；CNY 市值和成本按 BASE_TO_CNY rate 相乘，未实现损益为两者之差。",
      "inputs": ["quantity", "price", "cost_basis_original", "fx_rate", "valuation_as_of"],
      "output": "investment_valuation_metric_state",
      "outputs": ["market_value_original", "market_value_cny", "cost_basis_cny", "unrealized_pnl_cny"],
      "unit": "original currency and CNY",
      "parameters": ["PARAM-PFI-061..067"],
      "boundaries_zh": ["非 CNY 估值只接受 BASE_TO_CNY，CNY 用 identity 1。", "任一时点或来源依赖缺失时 value 为 null。"],
      "dependencies": ["FORM-PFI-009", "MOD-PFI-007", "SRC-MARKET-PRICES", "SRC-FX-SNAPSHOT"],
      "test_refs": ["PFI/tests/test_v025_stage4_holdings_valuation.py"],
      "effective_from": "2026-07-15",
      "formula_hash": "sha256:217c936b0d9ffc4f8ee4d0ae19b1644270585b2a461b96581ad5e43a4c4bb60a",
      "validation_status": "validated",
      "lifecycle_status": "active",
      "historical_compatibility_zh": "保留 Stage 4.2 PIT 与精确 Decimal 估值合同。"
    },
    {
      "formula_id": "FORM-PFI-011",
      "version": "pfi-v0.2.5-source-snapshot-sum-v1",
      "label_zh": "来源快照求和",
      "definition_zh": "只对完整、来源可证的 CNY snapshot values 求和，交易事件不得补造缺失余额。",
      "inputs": ["source_reported_snapshot_values", "source_state"],
      "output": "source_snapshot_sum_cny",
      "outputs": ["source_snapshot_sum_cny", "metric_state"],
      "unit": "CNY",
      "parameters": ["PARAM-PFI-068", "PARAM-PFI-069"],
      "boundaries_zh": ["非 ready dependency 阻断聚合并保持 null。", "confirmed_zero 必须有完整证据。"],
      "dependencies": ["MOD-PFI-008"],
      "test_refs": ["PFI/tests/test_v025_stage4_cross_page_consistency.py"],
      "effective_from": "2026-07-15",
      "formula_hash": "sha256:a698f3fc3d6bdc9b42ed01ca444f2b8480435c0dacadd64c451f27eb19a91bda",
      "validation_status": "validated",
      "lifecycle_status": "active",
      "historical_compatibility_zh": "保留 Stage 4.3 source-only 聚合和 null 传播。"
    },
    {
      "formula_id": "FORM-PFI-012",
      "version": "pfi-v0.2.5-net-worth-v1",
      "label_zh": "净资产组成",
      "definition_zh": "净资产等于账户资产加投资市值减负债；三个依赖全部 ready 或完整 confirmed_zero 才计算。",
      "inputs": ["account_assets_cny", "investment_market_value_cny", "liabilities_cny"],
      "output": "net_worth_cny",
      "outputs": ["net_worth_cny", "metric_state"],
      "unit": "CNY",
      "parameters": ["PARAM-PFI-059", "PARAM-PFI-060", "PARAM-PFI-069"],
      "boundaries_zh": ["缺失值不得转成零。", "任一非 ready dependency 使结果为 null。"],
      "dependencies": ["FORM-PFI-011", "MOD-PFI-008"],
      "test_refs": ["PFI/tests/test_v025_stage4_cross_page_consistency.py"],
      "effective_from": "2026-07-15",
      "formula_hash": "sha256:9cd617fd874c4fe106d844ad3858dc82a380161c1890f8388bdbaffb56ee97fd",
      "validation_status": "validated",
      "lifecycle_status": "active",
      "historical_compatibility_zh": "保留 Stage 4.3 三组件净资产与 fail-closed 规则。"
    },
    {
      "formula_id": "FORM-PFI-013",
      "version": "pfi-v0.2.5-unified-read-model-hash-v1",
      "label_zh": "统一 Read Model Hash",
      "definition_zh": "对排序后的依赖 hash 和排除页面身份、观察时间的 metric states 做 canonical JSON SHA256。",
      "inputs": ["dependency_hashes", "metric_states", "contract_hashes"],
      "output": "read_model_hash",
      "outputs": ["dependency_set_hash", "read_model_hash"],
      "unit": "sha256 identity",
      "parameters": ["PARAM-PFI-070", "PARAM-PFI-071", "PARAM-PFI-072"],
      "boundaries_zh": ["所有依赖必须是 lowercase sha256。", "页面身份和 observed_at 不进入 snapshot identity。"],
      "dependencies": ["FORM-PFI-011", "FORM-PFI-012", "MOD-PFI-008"],
      "test_refs": ["PFI/tests/test_v025_stage4_cross_page_consistency.py"],
      "effective_from": "2026-07-15",
      "formula_hash": "sha256:a3f6483dc89093afe9b0772431a53b91d13784945a3d70d4510996ae2df12db6",
      "validation_status": "validated",
      "lifecycle_status": "active",
      "historical_compatibility_zh": "保留 Stage 4.3 五 surface 同快照 hash。"
    },
    {
      "formula_id": "FORM-PFI-014",
      "version": "pfi-v0.2.5-cny-conversion-v1",
      "label_zh": "CNY/AUD 精确单位换算",
      "definition_zh": "CNY 原币按 identity 保持不变；AUD 金额仅按固定 AUD_TO_CNY 方向乘以 CNY/AUD 汇率，结果不在本层舍入。",
      "inputs": ["amount", "original_currency", "fx_rate", "fx_direction", "rate_unit"],
      "output": "amount_cny",
      "outputs": ["amount_cny"],
      "unit": "CNY",
      "parameters": ["PARAM-PFI-074", "PARAM-PFI-075", "PARAM-PFI-076"],
      "boundaries_zh": ["AUD/CNY 固定解释为 1 AUD = X CNY，禁止倒数推断。", "4.81 仅测试示例，生产默认必须为 null。", "只接受有限 Decimal；float、零或负汇率失败。"],
      "dependencies": ["FORM-PFI-002", "SRC-FX-SNAPSHOT"],
      "test_refs": ["PFI/tests/test_v025_stage5_formula_registry.py"],
      "effective_from": "2026-07-15",
      "formula_hash": "sha256:d9f3d8bc7ce0c05cabdc5a94e7f820013a8798e99a9ca50fcd34cc76cbec149f",
      "validation_status": "validated",
      "lifecycle_status": "active",
      "historical_compatibility_zh": "与 FORM-PFI-010 的 BASE_TO_CNY 乘法方向一致；不重写历史估值 hash。"
    },
    {
      "formula_id": "FORM-PFI-015",
      "version": "pfi-v0.2.5-dual-consumption-v1",
      "label_zh": "双消费与投资活动组件",
      "definition_zh": "消费总流出按版本化广义活动口径汇总生活消费、投资入金、投资域内配置与金融费用，并按已关联退款抵消；各组件同源展示且不得解释为净资产损失。",
      "inputs": ["financial_event_set", "source_record_id", "economic_event_id", "interconnection_group_id", "offset_economic_event_id"],
      "output": "dual_consumption_metrics",
      "outputs": ["total_consumption_outflow_cny", "living_consumption_cny", "investment_funding_outflow_cny", "investment_allocation_amount_cny", "financial_fee_outflow_cny", "refund_offset_cny"],
      "unit": "CNY",
      "parameters": ["PARAM-PFI-081", "PARAM-PFI-082", "PARAM-PFI-083", "PARAM-PFI-084", "PARAM-PFI-085"],
      "boundaries_zh": ["同一 source record 和同一 economic event/type 各只计一次。", "投资入金与域内配置是不同活动阶段，必须拆分展示并显式解释。", "退款必须唯一链接原事件，冲突或超额时失败关闭。"],
      "dependencies": ["FORM-PFI-004", "FORM-PFI-007", "MOD-PFI-010"],
      "test_refs": ["PFI/tests/test_v025_stage5_dual_consumption.py"],
      "effective_from": "2026-07-15",
      "formula_hash": "sha256:10b45da2fac5aa066aaf2ebc47d8615d6d144dbce6c09dd9bdbb2896ff3e57f2",
      "validation_status": "partial",
      "lifecycle_status": "active",
      "historical_compatibility_zh": "保留 v0.2.2 双口径事件集合，增加 source/economic-event 冲突失败与投资活动阶段解释。"
    },
    {
      "formula_id": "FORM-PFI-016",
      "version": "pfi-v0.2.5-core-financial-invariants-v1",
      "label_zh": "净资产、现金与投资重配置不变量",
      "definition_zh": "净资产等于现金、投资市值与其他资产之和减负债；现金按期初加流入减流出加调整滚动；投资重配置除显式费用外不得改变资产总额。",
      "inputs": ["core_financial_snapshot", "cash_rollforward", "investment_reallocation"],
      "output": "core_invariant_result",
      "outputs": ["net_worth_cny", "net_worth_discrepancy_cny", "cash_rollforward_discrepancy_cny", "investment_reallocation_discrepancy_cny", "ledger_conserved"],
      "unit": "CNY and invariant status",
      "parameters": ["PARAM-PFI-081"],
      "boundaries_zh": ["任一差异非精确零时失败关闭且不发布财务值。", "投资入金或买入本身不是净资产损失。", "Phase 5.2 只证明能力，真实数据不变量留给 Phase 5.3。"],
      "dependencies": ["FORM-PFI-008", "FORM-PFI-012", "MOD-PFI-010"],
      "test_refs": ["PFI/tests/test_v025_stage5_financial_invariants.py"],
      "effective_from": "2026-07-15",
      "formula_hash": "sha256:d09de306632fd79988c735abc49e9e94730f5c7b5505f133d8f1f9715232a755",
      "validation_status": "partial",
      "lifecycle_status": "active",
      "historical_compatibility_zh": "扩展 Stage 4 净资产和现金合同，不改写已验收的 not_loaded/null 当前状态。"
    },
    {
      "formula_id": "FORM-PFI-017",
      "version": "pfi-v0.2.5-investment-return-cost-drag-v1",
      "label_zh": "投资收益、成本与拖累",
      "definition_zh": "已实现净收益等于卖出收入减分摊成本、费用和税费；总净收益叠加未实现收益、分红和利息并扣持有成本，同时分别计算费用、税费、汇率与闲置现金拖累。",
      "inputs": ["market_value_cny", "remaining_cost_cny", "sell_proceeds_cny", "allocated_cost_cny", "fees_cny", "taxes_cny", "income_cny", "fx_exposure", "idle_cash_cny"],
      "output": "investment_metrics",
      "outputs": ["unrealized_pnl_cny", "realized_pnl_net_cny", "total_return_net_cny", "fee_drag_rate", "tax_drag_rate", "fx_drag_cny", "idle_cash_drag_cny"],
      "unit": "CNY and decimal rate",
      "parameters": ["PARAM-PFI-081"],
      "boundaries_zh": ["费用和税费只扣一次。", "分母为零时拖累率为 null，不伪造零。", "生产结果必须绑定持仓、价格、成本、FX 和交易 lineage。"],
      "dependencies": ["FORM-PFI-009", "FORM-PFI-010", "FORM-PFI-014", "MOD-PFI-010"],
      "test_refs": ["PFI/tests/test_v025_stage5_financial_invariants.py"],
      "effective_from": "2026-07-15",
      "formula_hash": "sha256:27843944f347cb6729fdb0b5abcf4c5e72d70067c2a78d8c84b7b52af5dbece8",
      "validation_status": "partial",
      "lifecycle_status": "active",
      "historical_compatibility_zh": "保留 v0.2.2 已实现/未实现收益与拖累含义，修正零分母为 null 并显式防止费用重复扣减。"
    },
    {
      "formula_id": "FORM-PFI-018",
      "version": "pfi-v0.2.5-xirr-v1",
      "label_zh": "日期感知投资 XIRR",
      "definition_zh": "按实际日期和 365 日基准求解使投资现金流净现值为零的年化收益率；投资入金为负，回流、分红、利息和终值为正。",
      "inputs": ["dated_investment_cashflows"],
      "output": "xirr",
      "outputs": ["xirr", "residual_abs", "iterations", "sign_change_count"],
      "unit": "annual decimal rate",
      "parameters": ["PARAM-PFI-081", "PARAM-PFI-089", "PARAM-PFI-090", "PARAM-PFI-091", "PARAM-PFI-092"],
      "boundaries_zh": ["至少一个负流和一个正流且日期不少于两个。", "多次符号变化导致潜在多根时标记 blocked，不选择任意根。", "无法括根或不收敛时失败关闭。"],
      "dependencies": ["FORM-PFI-017", "MOD-PFI-010"],
      "test_refs": ["PFI/tests/test_v025_stage5_financial_invariants.py"],
      "effective_from": "2026-07-15",
      "formula_hash": "sha256:14b8695fadf9dd361f462e060120b879dba7a136268f568d07a14f7ce73f69cf",
      "validation_status": "partial",
      "lifecycle_status": "active",
      "historical_compatibility_zh": "落实 v0.2.2 XIRR 正负现金流策略，新增多根与收敛失败边界。"
    },
    {
      "formula_id": "FORM-PFI-019",
      "version": "pfi-v0.2.5-seven-window-cashflow-v1",
      "label_zh": "七窗口外部现金流",
      "definition_zh": "按 as_of 对去重经济事件计算 7、21、30、60、90、180、360 日外部流入、外部流出和净现金流，内部转账单列且不进入净现金流。",
      "inputs": ["financial_event_set", "as_of"],
      "output": "cashflow_window_metrics",
      "outputs": ["external_inflow_cny", "external_outflow_cny", "internal_transfer_cny", "net_cashflow_cny"],
      "unit": "CNY by day window",
      "parameters": ["PARAM-PFI-081", "PARAM-PFI-086"],
      "boundaries_zh": ["窗口固定为 7/21/30/60/90/180/360。", "无事件窗口返回 filtered_empty/null，不显示假零。", "内部转账不改变体系外净现金流。"],
      "dependencies": ["FORM-PFI-004", "FORM-PFI-007", "FORM-PFI-015", "MOD-PFI-010"],
      "test_refs": ["PFI/tests/test_v025_stage5_dual_consumption.py"],
      "effective_from": "2026-07-15",
      "formula_hash": "sha256:e886fe19fce26640578da1c2e6d8ab45c83581b185e57120a13b23675cb94e30",
      "validation_status": "partial",
      "lifecycle_status": "active",
      "historical_compatibility_zh": "保留 v0.2.2 七窗口集合并应用 v0.2.5 economic-event 去重与 no-false-zero 状态。"
    },
    {
      "formula_id": "FORM-PFI-020",
      "version": "pfi-v0.2.5-taxonomy-tag-policy-v1",
      "label_zh": "分类与标签治理规则",
      "definition_zh": "分类保持 L1、L2 上限且每笔交易仅一个主分类；多维分析使用默认或自定义标签，保留停用历史并支持 all/any 视图筛选。",
      "inputs": ["taxonomy", "primary_category_assignments", "tag_definitions", "tag_history", "view_filter"],
      "output": "taxonomy_tag_validation",
      "outputs": ["taxonomy_validation", "primary_category_validation", "tag_policy_validation"],
      "unit": "governance decision",
      "parameters": ["PARAM-PFI-081", "PARAM-PFI-087", "PARAM-PFI-088"],
      "boundaries_zh": ["L1 不超过 12、单个 L1 的 L2 不超过 5、总 L2 不超过 50。", "每笔记录恰有一个主分类，多维维度使用标签。", "停用标签保留历史但不得用于新分配。"],
      "dependencies": ["MOD-PFI-010"],
      "test_refs": ["PFI/tests/test_v025_stage5_dual_consumption.py"],
      "effective_from": "2026-07-15",
      "formula_hash": "sha256:af21e5447bdd9f3d5528c328be4a9fcee236dfc99fb96a7f9f645740be1a2906",
      "validation_status": "partial",
      "lifecycle_status": "active",
      "historical_compatibility_zh": "直接保留 v0.2.2 taxonomy/tag 限制与历史语义，未执行数据库迁移。"
    }
  ]
}
